xontrib/hist_format.py
xontrib_hist_format-0.0.13.dist-info/LICENSE
xontrib_hist_format-0.0.13.dist-info/METADATA
xontrib_hist_format-0.0.13.dist-info/WHEEL
xontrib_hist_format-0.0.13.dist-info/top_level.txt
xontrib_hist_format-0.0.13.dist-info/RECORD
