Metadata-Version: 2.1
Name: xontrib-hist-format
Version: 0.0.13
Summary: Format xonsh history to post it to Github or another page.
Home-page: https://github.com/anki-code/xontrib-hist-format
Author: anki-code
Author-email: no@no.no
License: MIT
Project-URL: Documentation, https://github.com/anki-code/xontrib-hist-format/blob/master/README.md
Project-URL: Code, https://github.com/anki-code/xontrib-hist-format
Project-URL: Issue tracker, https://github.com/anki-code/xontrib-hist-format/issues
Platform: any
Classifier: Programming Language :: Python :: 3
Classifier: Programming Language :: Python :: 3.6
Classifier: Programming Language :: Python :: 3.7
Classifier: Programming Language :: Python :: 3.8
Classifier: License :: OSI Approved :: MIT License
Classifier: Operating System :: OS Independent
Classifier: Topic :: System :: Shells
Classifier: Topic :: System :: System Shells
Classifier: Topic :: Terminals
Requires-Python: >=3.6
License-File: LICENSE
